LICENSE
README.md
setup.py
src/dconf.py
src/dconf.egg-info/PKG-INFO
src/dconf.egg-info/SOURCES.txt
src/dconf.egg-info/dependency_links.txt
src/dconf.egg-info/top_level.txt