Metadata-Version: 2.1
Name: dconf
Version: 0.0.3
Summary: Easy dot representation configuration module.
Home-page: https://github.com/Anankke/dconf
Author: Anankke W
Author-email: anankke@pm.me
License: LICENSE
Project-URL: Bug Tracker, https://github.com/Anankke/dconf/issues
Platform: UNKNOWN
Classifier: Programming Language :: Python :: 3
Classifier: License :: OSI Approved :: MIT License
Classifier: Operating System :: OS Independent
Requires-Python: >=3.6
License-File: LICENSE
